oqd_core/__init__.py
oqd_core/backend/__init__.py
oqd_core/backend/base.py
oqd_core/backend/metric.py
oqd_core/backend/task.py
oqd_core/compiler/__init__.py
oqd_core/compiler/analog/__init__.py
oqd_core/compiler/analog/analysis.py
oqd_core/compiler/analog/error.py
oqd_core/compiler/analog/utils.py
oqd_core/compiler/analog/passes/__init__.py
oqd_core/compiler/analog/passes/analysis.py
oqd_core/compiler/analog/passes/assign.py
oqd_core/compiler/analog/passes/canonicalize.py
oqd_core/compiler/analog/rewrite/__init__.py
oqd_core/compiler/analog/rewrite/assign.py
oqd_core/compiler/analog/rewrite/canonicalize.py
oqd_core/compiler/analog/verify/__init__.py
oqd_core/compiler/analog/verify/canonicalize.py
oqd_core/compiler/analog/verify/operator.py
oqd_core/compiler/analog/verify/task.py
oqd_core/compiler/math/__init__.py
oqd_core/compiler/math/passes.py
oqd_core/compiler/math/rules.py
oqd_core/interface/__init__.py
oqd_core/interface/math.py
oqd_core/interface/unit.py
oqd_core/interface/analog/__init__.py
oqd_core/interface/analog/operation.py
oqd_core/interface/analog/operator.py
oqd_core/interface/atomic/__init__.py
oqd_core/interface/atomic/circuit.py
oqd_core/interface/atomic/protocol.py
oqd_core/interface/atomic/system.py
oqd_core/interface/digital/__init__.py
oqd_core/interface/digital/circuit.py
oqd_core/interface/digital/gate.py
oqd_core/interface/digital/register.py
oqd_core/interface/digital/statement.py
oqd_core-0.1.0.dist-info/LICENSE
oqd_core-0.1.0.dist-info/METADATA
oqd_core-0.1.0.dist-info/NOTICE
oqd_core-0.1.0.dist-info/WHEEL
oqd_core-0.1.0.dist-info/top_level.txt
oqd_core-0.1.0.dist-info/RECORD
