Metadata-Version: 2.1
Name: oqd-core
Version: 0.1.0
License: Apache 2.0
Project-URL: Homepage, https://github.com/OpenQuantumDesign/oqd-core
Project-URL: Repository, https://github.com/OpenQuantumDesign/oqd-core.git
Project-URL: Issues, https://github.com/OpenQuantumDesign/oqd-core/issues
Keywords: quantum,computing,analog,digital,compiler,transpilation,atomic
Classifier: Development Status :: 3 - Alpha
Classifier: Intended Audience :: Science/Research 
Classifier: Topic :: Scientific/Engineering :: Physics
Classifier: Topic :: Scientific/Engineering :: Information Analysis
Classifier: Topic :: Software Development :: Compilers
Classifier: License :: OSI Approved :: Apache Software License
Classifier: Programming Language :: Python :: 3
Classifier: Programming Language :: Python :: 3.10
Classifier: Programming Language :: Python :: 3.11
Classifier: Programming Language :: Python :: 3.12
Requires-Python: >=3.10
License-File: LICENSE
License-File: NOTICE
Requires-Dist: pydantic>=2.4
Requires-Dist: qutip==5.0.1
Requires-Dist: Cython~=3.0.10
Requires-Dist: filelock~=3.13.4
Requires-Dist: numpy~=1.0
Requires-Dist: oqd-compiler-infrastructure
Provides-Extra: docs
Requires-Dist: pymdown-extensions; extra == "docs"
Requires-Dist: mkdocstrings; extra == "docs"
Requires-Dist: mkdocs-material; extra == "docs"
Requires-Dist: mkdocstrings-python; extra == "docs"
Requires-Dist: mdx-truly-sane-lists; extra == "docs"
Provides-Extra: test
Requires-Dist: unittest-prettify; extra == "test"
